Workbook

Sheet Inputs
A1: year | B1: kind | C1: item | D1: amount_as_printed | E1: unit | F1: hkd_million | G1: source_url | H1: note
A2: 2022 | B2: funding | C2: Co-Investment Fund | Enterprises setting up in Hong Kong | D2: 30 | E2: HK$ billion | F2: =IF(E2="HK$ billion",D2*1000,IF(E2="HK$ million",D2,IF(E2="億元",D2*100,""))) -> 30000 | G2: https://www.ceo.gov.hk/public/open-data/en/policy_address/pa2022.xml | H2: Set aside from the Future Fund.
A3: 2022 | B3: funding | C3: RAISe+ Scheme | University research teams with potential to become start-ups | D3: 10 | E3: HK$ billion | F3: =IF(E3="HK$ billion",D3*1000,IF(E3="HK$ million",D3,IF(E3="億元",D3*100,""))) -> 10000 | G3: https://www.ceo.gov.hk/public/open-data/en/policy_address/pa2022.xml | H3: Earmarked for launch the next year, on a matching basis, for at least 100 teams.
A4: 2022 | B4: funding | C4: Strategic Tech Fund | Life and health technology, AI and data science, advanced manufacturing and new energy technology | D4: 5 | E4: HK$ billion | F4: =IF(E4="HK$ billion",D4*1000,IF(E4="HK$ million",D4,IF(E4="億元",D4*100,""))) -> 5000 | G4: https://www.ceo.gov.hk/public/open-data/en/policy_address/pa2022.xml | H4: Used with OASES. The goal of attracting at least 100 I&T enterprises is a target, not a second government sum.
A5: 2023 | B5: funding | C5: New Industrialisation Acceleration Scheme | Life and health technologies, AI and data science, advanced manufacturing, new energy technologies | D5: 10 | E5: HK$ billion | F5: =IF(E5="HK$ billion",D5*1000,IF(E5="HK$ million",D5,IF(E5="億元",D5*100,""))) -> 10000 | G5: https://www.ceo.gov.hk/public/open-data/en/policy_address/pa2023.xml | H5: Matching of 1 (Government) to 2 (company), funding ceiling HK$200 million.
A6: 2023 | B6: funding | C6: Film Development Fund and CreateSmart Initiative | Film, cultural and creative industries | D6: 4.3 | E6: HK$ billion | F6: =IF(E6="HK$ billion",D6*1000,IF(E6="HK$ million",D6,IF(E6="億元",D6*100,""))) -> 4300 | G6: https://www.ceo.gov.hk/public/open-data/en/policy_address/pa2023.xml | H6: One injection shared by the two schemes.
A7: 2024 | B7: funding | C7: Research Matching Grant Scheme | Research at institutions | D7: 1.5 | E7: HK$ billion | F7: =IF(E7="HK$ billion",D7*1000,IF(E7="HK$ million",D7,IF(E7="億元",D7*100,""))) -> 1500 | G7: https://www.ceo.gov.hk/public/open-data/en/policy_address/pa2024.xml | H7: Paragraph 78. A new round.
A8: 2024 | B8: funding | C8: I&T Industry-Oriented Fund | Life and health technology, AI and robotics, semi-conductors and smart devices, advanced materials, new energy | D8: 10 | E8: HK$ billion | F8: =IF(E8="HK$ billion",D8*1000,IF(E8="HK$ million",D8,IF(E8="億元",D8*100,""))) -> 10000 | G8: https://www.ceo.gov.hk/public/open-data/en/policy_address/pa2024.xml | H8: Fund-of-funds. The 2026 address says it is expected to launch in 2026.
A9: 2024 | B9: funding | C9: Innovation and Technology Venture Fund | Start-ups in strategic industries | D9: 1.5 | E9: HK$ billion | F9: =IF(E9="HK$ billion",D9*1000,IF(E9="HK$ million",D9,IF(E9="億元",D9*100,""))) -> 1500 | G9: https://www.ceo.gov.hk/public/open-data/en/policy_address/pa2024.xml | H9: Redeployed to set up funds jointly with the market, on a matching basis.
A10: 2024 | B10: funding | C10: I&T Accelerator Pilot Scheme | Start-up accelerators | D10: 180 | E10: HK$ million | F10: =IF(E10="HK$ billion",D10*1000,IF(E10="HK$ million",D10,IF(E10="億元",D10*100,""))) -> 180 | G10: https://www.ceo.gov.hk/public/open-data/en/policy_address/pa2024.xml | H10: Paragraph 80. Matching 1 to 2, subsidy ceiling HK$30 million.
A11: 2024 | B11: funding | C11: New Energy Transport Fund | Electric taxis and franchised buses, hydrogen fuel-cell heavy vehicles | D11: 750 | E11: HK$ million | F11: =IF(E11="HK$ billion",D11*1000,IF(E11="HK$ million",D11,IF(E11="億元",D11*100,""))) -> 750 | G11: https://www.ceo.gov.hk/public/open-data/en/policy_address/pa2024.xml | H11: Paragraph 85 says around HK$750 million.
A12: 2025 | B12: funding | C12: Frontier Technology Research Support Scheme | AI and other frontier research | D12: 3 | E12: HK$ billion | F12: =IF(E12="HK$ billion",D12*1000,IF(E12="HK$ million",D12,IF(E12="億元",D12*100,""))) -> 3000 | G12: https://www.ceo.gov.hk/public/open-data/en/policy_address/pa2025.xml | H12: Paragraph 68. Announced earlier. Applications to open soon.
A13: 2025 | B13: funding | C13: Hong Kong AI Research and Development Institute | AI research, transfer, and use cases | D13: 1 | E13: HK$ billion | F13: =IF(E13="HK$ billion",D13*1000,IF(E13="HK$ million",D13,IF(E13="億元",D13*100,""))) -> 1000 | G13: https://www.ceo.gov.hk/public/open-data/en/policy_address/pa2025.xml | H13: Paragraph 69. Earmarked for establishment in 2026.
... A26: 2026 | B26: outcome_ADT | C26: ADT | D26: 282.5 | E26: HK$ billion | F26: =IF(E26="HK$ billion",D26*1000,IF(E26="HK$ million",D26,IF(E26="億元",D26*100,""))) -> 282500 | G26: https://www.hkex.com.hk/Market-Data/Statistics/Consolidated-Reports/HKEX-Monthly-Market-Highlights?sc_lang=en | H26: 31 Aug 2026. Printed change +14%. First eight months, versus HK$248.3 billion a year earlier.

Sheet Year_after
A1: address_year | B1: outcome_year | C1: window | D1: stated_funding_hkd_million | E1: outcome_ipo_hkd_million | F1: funding_share_of_ipo | G1: outcome_adt_hkd_million
A2: 2022 | B2: 2023 | C2: 2023 full year | D2: =SUMIFS(Inputs!F:F,Inputs!A:A,A2,Inputs!B:B,"funding") -> 45000 | E2: =SUMIFS(Inputs!F:F,Inputs!A:A,B2,Inputs!B:B,"outcome_IPO") -> 46294.9 | F2: =IF(E2="", "", D2/E2) -> 0.97202932 | G2: =SUMIFS(Inputs!F:F,Inputs!A:A,B2,Inputs!B:B,"outcome_ADT") -> 105012
A3: 2023 | B3: 2024 | C3: 2024 full year | D3: =SUMIFS(Inputs!F:F,Inputs!A:A,A3,Inputs!B:B,"funding") -> 14300 | E3: =SUMIFS(Inputs!F:F,Inputs!A:A,B3,Inputs!B:B,"outcome_IPO") -> 87477.8 | F3: =IF(E3="", "", D3/E3) -> 0.16347005 | G3: =SUMIFS(Inputs!F:F,Inputs!A:A,B3,Inputs!B:B,"outcome_ADT") -> 131825
A4: 2024 | B4: 2025 | C4: 2025 full year | D4: =SUMIFS(Inputs!F:F,Inputs!A:A,A4,Inputs!B:B,"funding") -> 13930 | E4: =SUMIFS(Inputs!F:F,Inputs!A:A,B4,Inputs!B:B,"outcome_IPO") -> 286900 | F4: =IF(E4="", "", D4/E4) -> 0.048553503 | G4: =SUMIFS(Inputs!F:F,Inputs!A:A,B4,Inputs!B:B,"outcome_ADT") -> 249800
A5: 2025 | B5: 2026 | C5: 2026, first eight months | D5: =SUMIFS(Inputs!F:F,Inputs!A:A,A5,Inputs!B:B,"funding") -> 4100 | E5: =SUMIFS(Inputs!F:F,Inputs!A:A,B5,Inputs!B:B,"outcome_IPO") -> 342400 | F5: =IF(E5="", "", D5/E5) -> 0.011974299 | G5: =SUMIFS(Inputs!F:F,Inputs!A:A,B5,Inputs!B:B,"outcome_ADT") -> 282500
A6: 2026 | B6: not stated in source | C6: 2027 not published | D6: =SUMIFS(Inputs!F:F,Inputs!A:A,A6,Inputs!B:B,"funding") -> 3300 | E6: not stated in source | F6: not stated in source | G6: not stated in source
A8: Share = stated funding in the address year / IPO funds in the outcome window.
A9: 2026 IPO and ADT are the first eight months. Do not read that bar as a full year.
A10: 2027 is not stated in source, so the 2026 address has no share.

Sheet Chart_data
A1: outcome_window | B1: stated_funding_hkd_billion | C1: ipo_funds_hkd_billion
A2: =Year_after!C2 -> 2023 full year | B2: =Year_after!D2/1000 -> 45 | C2: =Year_after!E2/1000 -> 46.2949
A3: =Year_after!C3 -> 2024 full year | B3: =Year_after!D3/1000 -> 14.3 | C3: =Year_after!E3/1000 -> 87.4778
A4: =Year_after!C4 -> 2025 full year | B4: =Year_after!D4/1000 -> 13.93 | C4: =Year_after!E4/1000 -> 286.9
A5: =Year_after!C5 -> 2026, first eight months | B5: =Year_after!D5/1000 -> 4.1 | C5: =Year_after!E5/1000 -> 342.4

Sheet Industry
A1: policy_industry | B1: address_year | C1: outcome_window | D1: hkex_evidence | E1: amount_as_printed | F1: unit | G1: hkd_million | H1: board_ipo_hkd_million | I1: industry_share_of_ipo | J1: source_url | K1: note
A2: Life and health | B2: 2022 | C2: 2023 full year | D2: Sichuan Kelun-Biotech Biopharmaceutical, ten largest IPOs | E2: 1.56 | F2: HK$ billion | G2: =IF(F2="HK$ billion",E2*1000,IF(F2="HK$ million",E2,IF(F2="億元",E2*100,""))) -> 1560 | H2: 46294.9 | I2: =IF(OR(G2="",H2=""),"",G2/H2) -> 0.033697016 | J2: https://www.hkex.com.hk/-/media/HKEX-Market/Market-Data/Statistics/Consolidated-Reports/Annual-Market-Statistics/FY_2023-Annual-Market-Stat_Eng.pdf | K2: Market Statistics 2023, printed page 7. The printed name includes Biotech and the -B marker.
A3: New energy | B3: 2022 | C3: 2023 full year | D3: REPT BATTERO Energy, ten largest IPOs | E3: 2.12 | F3: HK$ billion | G3: =IF(F3="HK$ billion",E3*1000,IF(F3="HK$ million",E3,IF(F3="億元",E3*100,""))) -> 2120 | H3: 46294.9 | I3: =IF(OR(G3="",H3=""),"",G3/H3) -> 0.045793381 | J3: https://www.hkex.com.hk/-/media/HKEX-Market/Market-Data/Statistics/Consolidated-Reports/Annual-Market-Statistics/FY_2023-Annual-Market-Stat_Eng.pdf | K3: Market Statistics 2023, printed page 7. The printed name includes Energy.
A4: New energy | B4: 2022 | C4: 2023 full year | D4: Sino-Synergy Hydrogen Energy Technology, ten largest IPOs | E4: 1.56 | F4: HK$ billion | G4: =IF(F4="HK$ billion",E4*1000,IF(F4="HK$ million",E4,IF(F4="億元",E4*100,""))) -> 1560 | H4: 46294.9 | I4: =IF(OR(G4="",H4=""),"",G4/H4) -> 0.033697016 | J4: https://www.hkex.com.hk/-/media/HKEX-Market/Market-Data/Statistics/Consolidated-Reports/Annual-Market-Statistics/FY_2023-Annual-Market-Stat_Eng.pdf | K4: Market Statistics 2023, printed page 7. The printed name includes Hydrogen Energy.
A5: AI and robotics | B5: 2023 | C5: 2024 full year | D5: Horizon Robotics, ten largest IPOs | E5: 6.09 | F5: HK$ billion | G5: =IF(F5="HK$ billion",E5*1000,IF(F5="HK$ million",E5,IF(F5="億元",E5*100,""))) -> 6090 | H5: 87477.8 | I5: =IF(OR(G5="",H5=""),"",G5/H5) -> 0.069617663 | J5: https://www.hkex.com.hk/-/media/HKEX-Market/Market-Data/Statistics/Consolidated-Reports/Annual-Market-Statistics/2024FY-Ann-Mkt-Stat_eng.pdf | K5: Market Statistics 2024, printed page 7. The 2023 address says AI and data science. The printed name says Robotics.
A6: AI and robotics | B6: 2023 | C6: 2024 full year | D6: RoboSense Technology, ten largest IPOs | E6: 1.06 | F6: HK$ billion | G6: =IF(F6="HK$ billion",E6*1000,IF(F6="HK$ million",E6,IF(F6="億元",E6*100,""))) -> 1060 | H6: 87477.8 | I6: =IF(OR(G6="",H6=""),"",G6/H6) -> 0.01211736 | J6: https://www.hkex.com.hk/-/media/HKEX-Market/Market-Data/Statistics/Consolidated-Reports/Annual-Market-Statistics/2024FY-Ann-Mkt-Stat_eng.pdf | K6: Market Statistics 2024, printed page 7.
A7: Specialist technology | B7: 2023 | C7: 2024 full year | D7: Chapter 18C listings | E7: 3 | F7: companies | G7: =IF(F7="HK$ billion",E7*1000,IF(F7="HK$ million",E7,IF(F7="億元",E7*100,""))) | H7: not used | I7: not stated in source | J7: https://www.hkex.com.hk/-/media/HKEX-Market/News/News-Release/2025/250227news/250227_FY-Results_e.pdf | K7: 2024 Final Results, p.11. First Chapter 18C listing was 13 June 2024. The five 18C industries are not split.
A8: New economy, wider than the policy list | B8: 2023 | C8: 2024 full year | D8: Share of capital raised | E8: almost 82% | G8: =IF(F8="HK$ billion",E8*1000,IF(F8="HK$ million",E8,IF(F8="億元",E8*100,""))) | H8: not used | I8: not stated in source | J8: https://www.hkex.com.hk/-/media/HKEX-Market/News/News-Release/2025/250227news/250227_FY-Results_e.pdf | K8: 2024 Final Results, p.11. HKEX does not define new economy as the Policy Address industry list.
A9: Life and health | B9: 2024 | C9: 2025 full year | D9: Biotech Companies listed | E9: 16 | F9: companies | G9: =IF(F9="HK$ billion",E9*1000,IF(F9="HK$ million",E9,IF(F9="億元",E9*100,""))) | H9: not used | I9: not stated in source | J9: https://www.hkex.com.hk/-/media/HKEX-Market/Listing/How-We-Regulate/Listing-Committee/Listing-Committee-Report/AnnualRpt_2025dec.pdf | K9: Listing Committee Report 2025, p.3.
A10: Specialist technology | B10: 2024 | C10: 2025 full year | D10: Specialist Technology Companies listed | E10: 5 | F10: companies | G10: =IF(F10="HK$ billion",E10*1000,IF(F10="HK$ million",E10,IF(F10="億元",E10*100,""))) | H10: not used | I10: not stated in source | J10: https://www.hkex.com.hk/-/media/HKEX-Market/Listing/How-We-Regulate/Listing-Committee/Listing-Committee-Report/AnnualRpt_2025dec.pdf | K10: Listing Committee Report 2025, p.3. Combined with the 16 biotech listings, HK$19.8 billion.
A11: Life and health plus specialist technology | B11: 2024 | C11: 2025 full year | D11: Funds raised by the 16 biotech and 5 specialist technology listings | E11: 19.8 | F11: HK$ billion | G11: =IF(F11="HK$ billion",E11*1000,IF(F11="HK$ million",E11,IF(F11="億元",E11*100,""))) -> 19800 | H11: 285800 | I11: =IF(OR(G11="",H11=""),"",G11/H11) -> 0.069279216 | J11: https://www.hkex.com.hk/-/media/HKEX-Market/Listing/How-We-Regulate/Listing-Committee/Listing-Committee-Report/AnnualRpt_2025dec.pdf | K11: The page prints one combined sum. It is not split between the two chapters.
A12: Life and health | B12: 2024 | C12: 2025 full year | D12: HengRui Pharma, H-share listing | E12: 11.4 | F12: HK$ billion | G12: =IF(F12="HK$ billion",E12*1000,IF(F12="HK$ million",E12,IF(F12="億元",E12*100,""))) -> 11400 | H12: 285800 | I12: =IF(OR(G12="",H12=""),"",G12/H12) -> 0.039888034 | J12: https://www.hkex.com.hk/-/media/HKEX-Market/Listing/How-We-Regulate/Listing-Committee/Listing-Committee-Report/AnnualRpt_2025dec.pdf | K12: Listing Committee Report 2025, p.2. Named separately from the HK$19.8 billion. Not added to it.
A13: New energy | B13: 2024 | C13: 2025 full year | D13: Contemporary Amperex Technology, named among the largest IPOs | E13: not stated in source | F13: not stated in source | G13: =IF(F13="HK$ billion",E13*1000,IF(F13="HK$ million",E13,IF(F13="億元",E13*100,""))) | H13: not used | I13: not stated in source | J13: https://www.hkex.com.hk/-/media/HKEX-Market/Listing/How-We-Regulate/Listing-Committee/Listing-Committee-Report/AnnualRpt_2025dec.pdf | K13: Listing Committee Report 2025, p.2 names the company and does not print its proceeds.
A14: AI | B14: 2024 | C14: 2025 full year | D14: Hesai, WeRide and Pony AI, named as homecoming listings | E14: not stated in source | F14: not stated in source | G14: =IF(F14="HK$ billion",E14*1000,IF(F14="HK$ million",E14,IF(F14="億元",E14*100,""))) | H14: not used | I14: not stated in source | J14: https://www.hkex.com.hk/-/media/HKEX-Market/Listing/How-We-Regulate/Listing-Committee/Listing-Committee-Report/AnnualRpt_2025dec.pdf | K14: Listing Committee Report 2025, p.2. No separate proceeds.
A15: Semi-conductors | B15: 2024 | C15: 2025 full year | D15: No semiconductor IPO total | E15: not stated in source | F15: not stated in source | G15: =IF(F15="HK$ billion",E15*1000,IF(F15="HK$ million",E15,IF(F15="億元",E15*100,""))) | H15: not used | I15: not stated in source | J15: https://www.hkex.com.hk/-/media/HKEX-Market/Listing/How-We-Regulate/Listing-Committee/Listing-Committee-Report/AnnualRpt_2025dec.pdf | K15: The 2024 address names semi-conductors and smart devices. The 2025 Listing Committee report does not.
A16: Advanced materials | B16: 2024 | C16: 2025 full year | D16: No advanced-materials IPO total | E16: not stated in source | F16: not stated in source | G16: =IF(F16="HK$ billion",E16*1000,IF(F16="HK$ million",E16,IF(F16="億元",E16*100,""))) | H16: not used | I16: not stated in source | J16: https://www.hkex.com.hk/-/media/HKEX-Market/Listing/How-We-Regulate/Listing-Committee/Listing-Committee-Report/AnnualRpt_2023dec.pdf | K16: Advanced materials is one of five Chapter 18C industries, Listing Committee Report 2023, p.6. The 2025 count of five specialist technology listings is not split.
A17: Film and creative industries | B17: 2023 | C17: 2024 full year | D17: No film IPO line | E17: not stated in source | F17: not stated in source | G17: =IF(F17="HK$ billion",E17*1000,IF(F17="HK$ million",E17,IF(F17="億元",E17*100,""))) | H17: not used | I17: not stated in source | J17: https://www.hkex.com.hk/-/media/HKEX-Market/Market-Data/Statistics/Consolidated-Reports/Annual-Market-Statistics/2024FY-Ann-Mkt-Stat_eng.pdf | K17: Market Statistics 2024 does not report film or CreateSmart fundraising.
A18: Aerospace | B18: 2025 | C18: 2026, first eight months | D18: No aerospace IPO line | E18: not stated in source | F18: not stated in source | G18: =IF(F18="HK$ billion",E18*1000,IF(F18="HK$ million",E18,IF(F18="億元",E18*100,""))) | H18: not used | I18: not stated in source | J18: https://www.hkex.com.hk/Market-Data/Statistics/Consolidated-Reports/HKEX-Monthly-Market-Highlights?sc_lang=en | K18: The highlights page has no industry split. Cirrus Aircraft, HK$1.51 billion, is on the 2024 ten-largest list, before this earmark.
A19: Construction | B19: 2026 | C19: 2027 not published | D19: No construction IPO line | E19: not stated in source | F19: not stated in source | G19: =IF(F19="HK$ billion",E19*1000,IF(F19="HK$ million",E19,IF(F19="億元",E19*100,""))) | H19: not used | I19: not stated in source | J19: https://www.hkex.com.hk/Market-Data/Statistics/Consolidated-Reports/HKEX-Monthly-Market-Highlights?sc_lang=en | K19: The following year is not published.
A21: Share = this row's HK$ million / the board IPO total for the same window. Counts are not shares.
A22: The 2025 denominator is HK$285,800 million, the Listing Committee's HK$285.8 billion, because 19.8 and 11.4 are printed there.

Sheet C18_listings
A1: company | B1: listing_date | C1: year | D1: funds_hkd_million | E1: source_url
A2: XtalPi Holdings Ltd. | B2: 2024-06-13 | C2: 2024 | D2: 1036 | E2: https://www.hkexgroup.com/Media-Centre/Insight/Insight/2026/HKEX-Insight/18C-Explained?sc_lang=en
A3: Black Sesame International Holdings Ltd. | B3: 2024-08-08 | C3: 2024 | D3: 1036 | E3: https://www.hkexgroup.com/Media-Centre/Insight/Insight/2026/HKEX-Insight/18C-Explained?sc_lang=en
A4: Shenzhen Dobot Corp. Ltd. | B4: 2024-12-23 | C4: 2024 | D4: 831 | E4: https://www.hkexgroup.com/Media-Centre/Insight/Insight/2026/HKEX-Insight/18C-Explained?sc_lang=en
A5: Beijing Yunji Technology Co., Ltd. | B5: 2025-10-16 | C5: 2025 | D5: 759 | E5: https://www.hkexgroup.com/Media-Centre/Insight/Insight/2026/HKEX-Insight/18C-Explained?sc_lang=en
A6: Deepexi Technology Co., Ltd. | B6: 2025-10-28 | C6: 2025 | D6: 710 | E6: https://www.hkexgroup.com/Media-Centre/Insight/Insight/2026/HKEX-Insight/18C-Explained?sc_lang=en
A7: WeRide Inc. | B7: 2025-11-06 | C7: 2025 | D7: 2392 | E7: https://www.hkexgroup.com/Media-Centre/Insight/Insight/2026/HKEX-Insight/18C-Explained?sc_lang=en
A8: CiDi Inc. | B8: 2025-12-19 | C8: 2025 | D8: 1422 | E8: https://www.hkexgroup.com/Media-Centre/Insight/Insight/2026/HKEX-Insight/18C-Explained?sc_lang=en
A9: Beijing 51World Digital Twin Technology Co., Ltd. | B9: 2025-12-30 | C9: 2025 | D9: 731 | E9: https://www.hkexgroup.com/Media-Centre/Insight/Insight/2026/HKEX-Insight/18C-Explained?sc_lang=en
A10: Shanghai Biren Technology Co., Ltd. | B10: 2026-01-02 | C10: 2026 | D10: 6420 | E10: https://www.hkexgroup.com/Media-Centre/Insight/Insight/2026/HKEX-Insight/18C-Explained?sc_lang=en
A11: Knowledge Atlas Technology JSC Ltd. | B11: 2026-01-08 | C11: 2026 | D11: 5000 | E11: https://www.hkexgroup.com/Media-Centre/Insight/Insight/2026/HKEX-Insight/18C-Explained?sc_lang=en
A12: MiniMax Group Inc. | B12: 2026-01-09 | C12: 2026 | D12: 5540 | E12: https://www.hkexgroup.com/Media-Centre/Insight/Insight/2026/HKEX-Insight/18C-Explained?sc_lang=en
A13: Guangdong Huayan Robotics Co., Ltd. | B13: 2026-03-30 | C13: 2026 | D13: 1579 | E13: https://www.hkexgroup.com/Media-Centre/Insight/Insight/2026/HKEX-Insight/18C-Explained?sc_lang=en
... A15: Shanghai FourSemi Semiconductor Co., Ltd. | B15: 2026-03-31 | C15: 2026 | D15: 480 | E15: https://www.hkexgroup.com/Media-Centre/Insight/Insight/2026/HKEX-Insight/18C-Explained?sc_lang=en
A17: Page total, HK$ billion, as printed | B17: 28.4
A18: Sum of the rows, HK$ million | B18: =SUM(D2:D15) -> 28435

Sheet C18_before_after
A1: year | B1: c18_listings | C1: c18_funds_hkd_million | D1: base_rate_year_end | E1: southbound_adt_hkd_billion | F1: board_ipo_hkd_million | G1: c18_share_of_board_ipo | H1: note
A2: 2022 | B2: =COUNTIF(C18_listings!C:C,A2) -> 0 | C2: =SUMIF(C18_listings!C:C,A2,C18_listings!D:D) -> 0 | D2: 0.0475 | E2: 31.7 | F2: 104570.3 | G2: =IF(F2="", "", C2/F2) -> 0 | H2: Before Chapter 18C. Base Rate end-2022. Southbound ADT. IPO from Market Statistics 2022.
A3: 2023 | B3: =COUNTIF(C18_listings!C:C,A3) -> 0 | C3: =SUMIF(C18_listings!C:C,A3,C18_listings!D:D) -> 0 | D3: 0.0575 | E3: 31.1 | F3: 46294.9 | G3: =IF(F3="", "", C3/F3) -> 0 | H3: Chapter effective 31 Mar 2023. No 18C listing this year. Base Rate end-2023 was 5.75%.
A4: 2024 | B4: =COUNTIF(C18_listings!C:C,A4) -> 3 | C4: =SUMIF(C18_listings!C:C,A4,C18_listings!D:D) -> 2903 | D4: 0.0475 | E4: 48.2 | F4: 87477.8 | G4: =IF(F4="", "", C4/F4) -> 0.033185563 | H4: Three 18C listings. Base Rate cut from 5.75% to 4.75%. Southbound ADT HK$48.2 billion.
A5: 2025 | B5: =COUNTIF(C18_listings!C:C,A5) -> 5 | C5: =SUMIF(C18_listings!C:C,A5,C18_listings!D:D) -> 6014 | D5: 0.04 | E5: 121.1 | F5: 285800 | G5: =IF(F5="", "", C5/F5) -> 0.021042687 | H5: Five 18C listings. Base Rate cut from 4.75% to 4.00%. Southbound ADT HK$121.1 billion. Board IPO is the Listing Committee figure.
A6: 2026 | B6: =COUNTIF(C18_listings!C:C,A6) -> 6 | C6: =SUMIF(C18_listings!C:C,A6,C18_listings!D:D) -> 19518 | D6: not stated in source | E6: not stated in source | F6: not stated in source | G6: not stated in source | H6: Listings through 31 Mar 2026 only. A full-year Base Rate, Southbound ADT and board IPO are not stated in source.
A8: Chapter 18C effective 31 March 2023. First listing 13 June 2024.
A9: The I&T Industry-Oriented Fund has no disbursement date in the 2026 Policy Address. It is not in this table.
A10: 2022 Base Rate: HKMA Annual Report 2022. 2023 and 2024: HKMA Annual Report 2024. 2025: HKMA Annual Report 2025.
A11: Southbound ADT: HKEX Stock Connect 2025 Review, February 2026.
